Workbook
Name Interest.Charge: Interest.Expense
Name Interest.Expense: Interest!$B$13

Sheet Assumptions
A1: Helios legacy plan - assumptions
A3: Interest rate (average debt) | B3: 0.06
A4: Opening debt FY24 | B4: 1000
A5: Scheduled repayment FY24 | B5: -250
A6: EBITDA FY24 | B6: 400
A7: EBITDA FY25 | B7: 430

Sheet Debt Schedule
A1: Helios legacy plan - debt schedule
A10: Debt roll-forward | B10: FY24 | C10: FY25
A11: Beginning Debt Balance | B11: =Assumptions!B4 -> 1000 | C11: =B14 -> 720
A12: Interest Expense | B12: =Interest!B13 -> 60 | C12: =Interest!C13 -> 43.2
A13: Free Cash Sweep | B13: =-'Cash Flow'!B12 -> -340 | C13: =-'Cash Flow'!C12 -> -386.8
A14: Ending Debt Balance | B14: =B11+B12+B13 -> 720 | C14: =C11+C12+C13 -> 376.4

Sheet Interest
A1: Helios legacy plan - interest
A10: Interest schedule | B10: FY24 | C10: FY25
A11: Interest rate | B11: =Assumptions!$B$3 -> 0.06 | C11: =B11 -> 0.06
A12: Average Debt Balance | B12: =('Debt Schedule'!B11+'Debt Schedule'!B11)/2 -> 1000 | C12: =('Debt Schedule'!C11+'Debt Schedule'!C11)/2 -> 720
A13: Interest Expense | B13: =B12*B11 -> 60 | C13: =C12*C11 -> 43.2

Sheet Cash Flow
A1: Helios legacy plan - cash flow
A10: Cash flow statement | B10: FY24 | C10: FY25
A11: EBITDA | B11: =Assumptions!B6 -> 400 | C11: =Assumptions!B7 -> 430
A12: Free Cash Flow | B12: =B11-Interest!B13 -> 340 | C12: =C11-Interest!C13 -> 386.8
A14: Total interest (named) | B14: =Interest.Charge -> 60

Sheet Rollforward
A1: Helios legacy plan - cash roll-forward
A10: Rolling cash balance | B10: FY24 | C10: FY25
A11: Opening Balance | B11: 1000 | C11: =B13 -> 880
A12: Net Movement | B12: -120 | C12: -80
A13: Closing Balance | B13: =SUM(B11:B12) -> 880 | C13: =SUM(C11:C12) -> 800

Sheet Iterative Block
A1: Helios legacy plan - iterative block
A10: Converging balance | B10: FY24
A11: Converging balance | B11: =B12/2 -> 0
A12: Converging balance | B12: =B11+100 -> 0
