Workbook
Name GrowthRate: Assumptions!$B$1
Name GrossMargin: Assumptions!$B$2
Name MonthlyOpex: Assumptions!$B$3
Name SeedRevenue: Assumptions!$B$4

Sheet Assumptions
A1: Growth Rate | B1: 0.08
A2: Gross Margin | B2: 0.72
A3: Monthly OpEx | B3: 250000
A4: Seed Revenue (M0) | B4: 1200000

Sheet Revenue
A1: M0 | B1: M1 | C1: M2 | D1: M3 | E1: M4 | F1: M5 | G1: M6 | H1: M7 | I1: M8 | J1: M9 | K1: M10 | L1: M11
A2: =SeedRevenue -> 1200000 | B2: =A2*(1+GrowthRate/12) -> 1208000 | C2: =B2*(1+GrowthRate/12) -> 1216053.3 | D2: =C2*(1+GrowthRate/12) -> 1224160.4 | E2: =D2*(1+GrowthRate/12) -> 1232321.4 | F2: =E2*(1+GrowthRate/12) -> 1240536.9 | G2: =F2*(1+GrowthRate/12) -> 1248807.1 | H2: =G2*(1+GrowthRate/12) -> 1257132.5 | I2: =H2*(1+GrowthRate/12) -> 1265513.4 | ... L2: =K2*(1+GrowthRate/12) -> 1290992.8

Sheet P&L
A1: Operating Profit (per month)
A2: =Revenue!A2-(Revenue!A2*(1-GrossMargin))-MonthlyOpex -> 614000 | B2: =Revenue!B2-(Revenue!B2*(1-GrossMargin))-MonthlyOpex -> 619760 | C2: =Revenue!C2-(Revenue!C2*(1-GrossMargin))-MonthlyOpex -> 625558.4 | D2: =Revenue!D2-(Revenue!D2*(1-GrossMargin))-MonthlyOpex -> 631395.46 | E2: =Revenue!E2-(Revenue!E2*(1-GrossMargin))-MonthlyOpex -> 637271.43 | F2: =Revenue!F2-(Revenue!F2*(1-GrossMargin))-MonthlyOpex -> 643186.57 | G2: =Revenue!G2-(Revenue!G2*(1-GrossMargin))-MonthlyOpex -> 649141.15 | H2: =Revenue!H2-(Revenue!H2*(1-GrossMargin))-MonthlyOpex -> 655135.42 | ... L2: =Revenue!L2-(Revenue!L2*(1-GrossMargin))-MonthlyOpex -> 679514.81
